inverso/__init__.py
inverso/__main__.py
inverso/api.py
inverso/cli.py
inverso/implementation.py
inverso-2025.11.16.dist-info/licenses/LICENSE
inverso-2025.11.16.dist-info/METADATA
inverso-2025.11.16.dist-info/WHEEL
inverso-2025.11.16.dist-info/entry_points.txt
inverso-2025.11.16.dist-info/top_level.txt
inverso-2025.11.16.dist-info/RECORD
